README.rst
setup.py
django_symmetric.egg-info/PKG-INFO
django_symmetric.egg-info/SOURCES.txt
django_symmetric.egg-info/dependency_links.txt
django_symmetric.egg-info/requires.txt
django_symmetric.egg-info/top_level.txt
symmetric/__init__.py
symmetric/authorization.py
symmetric/exceptions.py
symmetric/filters.py
symmetric/functions.py
symmetric/html.py
symmetric/middleware.py
symmetric/models.py
symmetric/response.py
symmetric/urls.py
symmetric/views.py
symmetric/xml.py
symmetric/management/__init__.py
symmetric/management/codeemitter.py
symmetric/management/functions.py
symmetric/management/generateconnections.py
symmetric/management/generatemodels.py
symmetric/management/overrides.py
symmetric/management/rules.py
symmetric/management/translate.py
symmetric/management/commands/__init__.py
symmetric/management/commands/documentapi.py
symmetric/management/commands/generateandroidconnections.py
symmetric/management/commands/generateandroidmodels.py
symmetric/management/commands/generatebackbonemodels.py
symmetric/management/commands/generateiosconnections.py
symmetric/management/commands/generateiosmodels.py
symmetric/management/commands/generatewindowsmodels.py
symmetric/management/commands/obfuscatesettings.py
symmetric/management/templates/android-connection.java
symmetric/management/templates/android-model.java
symmetric/management/templates/eslintrc
symmetric/management/templates/ios-connection.h
symmetric/management/templates/ios-connection.m
symmetric/management/templates/ios-model.h
symmetric/management/templates/ios-model.m
symmetric/management/templates/windows-model.cs