Metadata-Version: 1.1
Name: django-symmetric
Version: 0.0.6
Summary: RESTful Django API views to ease automation of creating symmetric client-side code.
Home-page: https://github.com/symmetricapi/django-symmetric
Author: mvx24
Author-email: cram2400@gmail.com
License: MIT
Keywords: django restful api views backbone java android ios
Platform: UNKNOWN
Classifier: Development Status :: 3 - Alpha
Classifier: Environment :: Console
Classifier: Framework :: Django
Classifier: License :: OSI Approved :: MIT License
Classifier: Operating System :: MacOS :: MacOS X
Classifier: Operating System :: POSIX
Classifier: Operating System :: Unix
Classifier: Programming Language :: Python :: 2.7
Classifier: Programming Language :: Python :: 2 :: Only
Classifier: Topic :: Database
Classifier: Topic :: Software Development :: Code Generators
Classifier: Topic :: Software Development :: Libraries :: Python Modules
